Metadata-Version: 2.1
Name: rapid-email-2
Version: 2.0
Summary: Sending email notification.
Author: Abhishek Negi
